{
  "generated_at": "2026-01-10T01:18:17.048935+08:00",
  "total_titles_processed": 374,
  "failed_sources": [],
  "trends": [
    {
      "keyword_group": "股票",
      "match_count": 1,
      "titles": [
        {
          "title": "航天电子：股票交易异常波动",
          "url": "https://www.toutiao.com/trending/7593021166730838052/",
          "source": "今日头条",
          "ranks": [
            16
          ],
          "is_new": false,
          "appearance_count": 2,
          "time_info": "[01时17分 ~ 01时18分]"
        }
      ]
    }
  ],
  "report_image_url": "https://joyce677.github.io/TrendRadar/img/news.jpg"
}