{
  "generated_at": "2026-04-06T20:52:39.420040+08:00",
  "total_titles_processed": 1349,
  "failed_sources": [],
  "trends": [
    {
      "keyword_group": "股票",
      "match_count": 2,
      "titles": [
        {
          "title": "马来西亚发起鼓励本地投资者购买股票的活动。",
          "url": "https://flash.jin10.com/detail/20260406050607153800",
          "source": "金十数据",
          "ranks": [
            13,
            30
          ],
          "is_new": false,
          "appearance_count": 2,
          "time_info": "[06时22分 ~ 07时26分]"
        },
        {
          "title": "CrowdStrike(CRWD.O)宣布将股票回购计划增加5亿美元至15亿美元。",
          "url": "https://flash.jin10.com/detail/20260406203045324800",
          "source": "金十数据",
          "ranks": [
            6
          ],
          "is_new": true,
          "appearance_count": 1,
          "time_info": "20时52分"
        }
      ]
    }
  ],
  "report_image_url": "https://joyce677.github.io/TrendRadar/img/news.jpg"
}