{
  "generated_at": "2026-07-06T11:26:01.102199+08:00",
  "total_titles_processed": 798,
  "failed_sources": [],
  "trends": [
    {
      "keyword_group": "股票",
      "match_count": 1,
      "titles": [
        {
          "title": "上周逾百亿资金回流股票ETF，硬科技板块热度居高不下",
          "url": "https://wallstreetcn.com/livenews/3129030",
          "source": "华尔街见闻-快讯",
          "ranks": [
            3,
            10
          ],
          "is_new": false,
          "appearance_count": 2,
          "time_info": "[06时54分 ~ 07时59分]"
        }
      ]
    }
  ],
  "report_image_url": "https://joyce677.github.io/TrendRadar/img/news.jpg"
}