{
  "generated_at": "2026-04-12T17:39:19.791013+08:00",
  "total_titles_processed": 1109,
  "failed_sources": [],
  "trends": [
    {
      "keyword_group": "股票",
      "match_count": 1,
      "titles": [
        {
          "title": "长药退：公司股票终止上市，将在2026年4月13日被摘牌。",
          "url": "https://wallstreetcn.com/livenews/3086356",
          "source": "华尔街见闻-快讯",
          "ranks": [
            4,
            7
          ],
          "is_new": false,
          "appearance_count": 2,
          "time_info": "[16时50分 ~ 17时39分]"
        }
      ]
    }
  ],
  "report_image_url": "https://joyce677.github.io/TrendRadar/img/news.jpg"
}