{
  "generated_at": "2025-11-12T01:13:20.398322+08:00",
  "total_titles_processed": 392,
  "failed_sources": [],
  "trends": [
    {
      "keyword_group": "股票",
      "match_count": 1,
      "titles": [
        {
          "title": "Prosus于11月3-7日按均价59.9133欧元回购股票90.2724万股，总计0.541亿欧元（折合0.623亿美元）。 Naspers同期按均价1232.2187南非兰特回购股票39.0090万股，总计4.807亿兰特（折合0.276亿美元）。",
          "url": "https://wallstreetcn.com/livenews/3002878",
          "source": "华尔街见闻-快讯",
          "ranks": [
            11,
            27
          ],
          "is_new": false,
          "appearance_count": 2,
          "time_info": "[00时17分 ~ 01时13分]"
        }
      ]
    }
  ],
  "report_image_url": "https://joyce677.github.io/TrendRadar/img/news.jpg"
}