{
  "generated_at": "2026-02-16T01:19:52.865892+08:00",
  "total_titles_processed": 341,
  "failed_sources": [],
  "trends": [
    {
      "keyword_group": "股票",
      "match_count": 1,
      "titles": [
        {
          "title": "分析师：AI风险主导市场 投资者抛售相关股票",
          "url": "https://flash.jin10.com/detail/20260215225328791800",
          "source": "金十数据",
          "ranks": [
            2
          ],
          "is_new": false,
          "appearance_count": 2,
          "time_info": "[00时20分 ~ 01时19分]"
        }
      ]
    }
  ],
  "report_image_url": "https://joyce677.github.io/TrendRadar/img/news.jpg"
}